dynamo2relion/__init__.py
dynamo2relion/_utils.py
dynamo2relion/_version.py
dynamo2relion/dynamo2relion.py
dynamo2relion-1.0.0.dist-info/LICENSE.txt
dynamo2relion-1.0.0.dist-info/METADATA
dynamo2relion-1.0.0.dist-info/WHEEL
dynamo2relion-1.0.0.dist-info/entry_points.txt
dynamo2relion-1.0.0.dist-info/top_level.txt
dynamo2relion-1.0.0.dist-info/RECORD
