Metadata-Version: 2.1
Name: dynamo2relion
Version: 1.0.0
Summary: Converts Dynamo table files to RELION star files
Author: Euan Pyle
Author-email: euanpyle@gmail.com
License: BSD 3-Clause License
Project-URL: homepage, https://github.com/EuanPyle/dynamo2relion
Project-URL: repository, https://github.com/EuanPyle/dynamo2relion
Classifier: Development Status :: 3 - Alpha
Classifier: License :: OSI Approved :: BSD License
Classifier: Programming Language :: Python :: 3
Classifier: Programming Language :: Python :: 3.6
Classifier: Programming Language :: Python :: 3.7
Classifier: Programming Language :: Python :: 3.8
Classifier: Programming Language :: Python :: 3.9
Classifier: Programming Language :: Python :: 3.10
Requires-Python: >=3.6
License-File: LICENSE.txt
Requires-Dist: starfile
Requires-Dist: dynamotable
Requires-Dist: eulerangles
Requires-Dist: typer
Requires-Dist: pandas
Provides-Extra: test
Requires-Dist: pytest (>=6.0) ; extra == 'test'
Requires-Dist: pytest-cov ; extra == 'test'
